[{"i": 3078, "type": "item", "zh": "集齐一定数量的“桂花”，可兑换珍贵好礼哦！"}, {"i": 3079, "type": "item", "zh": "使用后可获得1元充值卡x10和下一等级礼包"}, {"i": 3080, "type": "item", "zh": "盒子里蕴藏着八神裤子的秘密，赶紧打开它吧！"}, {"i": 3081, "type": "item", "zh": "集齐一定数量，可在女生日活动中兑换精美道具"}, {"i": 3082, "type": "item", "zh": "集齐一定数量的“雪花”，可兑换珍贵好礼哦！"}, {"i": 3083, "type": "item", "zh": "有几率开出钻石招募币、扭蛋机币、金币招募币"}, {"i": 3084, "type": "item", "zh": "恭喜高尼茨（女）获得第2届拳魂创造营冠军！"}, {"i": 3085, "type": "item", "zh": "从伊格尼斯、高尼茨、吉斯武器中选择一个获得"}, {"i": 3086, "type": "item", "zh": "集齐一定数量的“特训勋章”可兑换珍贵好礼哦"}, {"i": 3087, "type": "item", "zh": "挑选一件称手的兵器，然后打遍天下无敌手吧！"}, {"i": 3088, "type": "item", "zh": "伊格尼兹、无名、雅典娜02武器随机获得1个"}, {"i": 3089, "type": "item", "zh": "使用后等于在商城中充值200000档位1次"}, {"i": 3090, "type": "item", "zh": "使用后可获得1元充值卡x15和下一等级礼包"}, {"i": 3091, "type": "item", "zh": "从八神庵、安琪儿、莉安娜武器中随机获得一个"}, {"i": 3092, "type": "item", "zh": "“希望你明白，我……也是名义上的女主角。”"}, {"i": 3093, "type": "item", "zh": "使用后可获得1元充值卡x50和下一等级礼包"}, {"i": 3094, "type": "item", "zh": "“如果哪一天我自爆了，记得收集我的碎片。”"}, {"i": 3095, "type": "item", "zh": "英勇青铜？衷心希望你的定位赛可不是这个颜色"}, {"i": 3096, "type": "item", "zh": "使用后可获得1元充值卡x80和下一等级礼包"}, {"i": 3097, "type": "item", "zh": "提升己方女性格斗家2000生命和5%伤害率"}, {"i": 3098, "type": "item", "zh": "集齐一定数量的“七彩之星“可兑换珍贵好礼哦"}, {"i": 3099, "type": "item", "zh": "从伊格尼斯、高尼茨、吉斯武器中随机获得一个"}, {"i": 3100, "type": "item", "zh": "空手、斋祀、壬无月斩红郎武器中选择一个获得"}, {"i": 3101, "type": "item", "zh": "提升自身180攻击，8%格挡率和6%免伤率"}, {"i": 3102, "type": "item", "zh": "唐福禄、牙神幻十郎、高尼茨（女）武器3选1"}, {"i": 3103, "type": "item", "zh": "“我想想……找到父亲和升到7星哪个更难？”"}, {"i": 3104, "type": "item", "zh": "使用后可获得1元充值卡x90和下一等级礼包"}, {"i": 3105, "type": "item", "zh": "橙色康乃馨代表着...等等有橙色康乃馨吗?"}, {"i": 3106, "type": "item", "zh": "100点可可经验可合成1个经验巧克力（小）"}, {"i": 3107, "type": "item", "zh": "使用后等于在商城中充值100000档位1次"}, {"i": 3108, "type": "item", "zh": "打开后获得大量流派残页，残页数量随等级提升"}, {"i": 3109, "type": "item", "zh": "高仿的八尺琼勾玉，八神庵全球后援会人手一件"}, {"i": 3110, "type": "item", "zh": "提升自身180攻击，8%暴击率和6%伤害率"}, {"i": 3111, "type": "item", "zh": "提升己方全体200攻击，3%暴击，3%抗暴"}, {"i": 3112, "type": "item", "zh": "为获得社团格斗场冠军的玩家准备的荣誉奖杯。"}, {"i": 3113, "type": "item", "zh": "暴走八神庵、吉斯、伊格尼兹武器随机获得1个"}, {"i": 3114, "type": "item", "zh": "从八神庵、安琪儿、莉安娜武器中选择一个获得"}, {"i": 3115, "type": "item", "zh": "BT版本2周年专属藏品，感谢大家的陪伴！"}, {"i": 3116, "type": "item", "zh": "恭喜麻宫雅典娜获得第2届拳魂创造营八强！"}, {"i": 3117, "type": "item", "zh": "恭喜麻宫雅典娜获得第2届拳魂创造营亚军！"}, {"i": 3118, "type": "item", "zh": "恭喜麻宫雅典娜获得第2届拳魂创造营冠军！"}, {"i": 3119, "type": "item", "zh": "恭喜雅典娜02获得第2届拳魂创造营四强！"}, {"i": 3120, "type": "item", "zh": "“当年自爆的时候，我的确是变成了碎片。”"}, {"i": 3121, "type": "item", "zh": "恭喜雅典娜02获得第2届拳魂创造营冠军！"}, {"i": 3122, "type": "item", "zh": "恭喜雅典娜02获得第2届拳魂创造营亚军！"}, {"i": 3123, "type": "item", "zh": "香气迷人，口感松软，交融出绝妙的好滋味。"}, {"i": 3124, "type": "item", "zh": "一口甜蜜蜜，一口糯叽叽，吃了心情美滋滋。"}, {"i": 3125, "type": "item", "zh": "莉姆露露、蕾拉、天草四郎武器随机获得1个"}, {"i": 3126, "type": "item", "zh": "高尼茨、觉醒莉安娜、暴走八神庵武器3选1"}, {"i": 3127, "type": "item", "zh": "象征着团聚与丰收，对未来一切美好的祝愿。"}, {"i": 3128, "type": "item", "zh": "象征着团聚与丰收和对未来一切美好的祝愿。"}, {"i": 3129, "type": "item", "zh": "香甜的糕点上披着厚厚的一层奶油，美味至极"}, {"i": 3130, "type": "item", "zh": "雅典娜02最喜爱的短裙，洋溢着青春和时尚"}, {"i": 3131, "type": "item", "zh": "蕴藏攻之力，格斗家潜能突破的必备材料之一"}, {"i": 3132, "type": "item", "zh": "打开后获得唐福禄绝学*2，唐福禄纹章*2"}, {"i": 3133, "type": "item", "zh": "提升自身1200生命和对技格斗家3%伤害"}, {"i": 3134, "type": "item", "zh": "“希望所有的碎片都能成为大蛇的一部分。”"}, {"i": 3135, "type": "item", "zh": "恭喜麻宫雅典娜获得第2届拳魂创造营四强！"}, {"i": 3136, "type": "item", "zh": "蕴藏英灵之魂的结晶，散发出强大的灵魂之力"}, {"i": 3137, "type": "item", "zh": "恭喜雅典娜02获得第2届拳魂创造营八强！"}, {"i": 3138, "type": "item", "zh": "可获得加成：攻击+800，生命+9600"}, {"i": 3139, "type": "item", "zh": "两周年纪念勋章，见证了您不曾停止的战斗。"}, {"i": 3140, "type": "item", "zh": "集齐一定数量的“福”，可兑换珍贵好礼哦！"}, {"i": 3141, "type": "item", "zh": "使用后可获得1元充值卡x5和下一等级礼包"}, {"i": 3142, "type": "item", "zh": "种子是很诚实的，你付出什么，它就回报什么"}, {"i": 3143, "type": "item", "zh": "蕴藏技之力，格斗家潜能突破的必备材料之一"}, {"i": 3144, "type": "item", "zh": "提升自身2000生命和对技格斗家5%伤害"}, {"i": 3145, "type": "item", "zh": "可获得加成：攻击+500，生命+6000"}, {"i": 3146, "type": "item", "zh": "从阿修、伊丽莎白、堕珑武器中随机一个获得"}, {"i": 3147, "type": "item", "zh": "藤堂香澄、库拉、安琪儿、橘右京武器4选1"}, {"i": 3148, "type": "item", "zh": "喝下的是酒，泛起的是愁。切忌一人饮酒醉啊"}, {"i": 3149, "type": "item", "zh": "精心挑选中药材，自制静康防疫驱蚊香囊包."}, {"i": 3150, "type": "item", "zh": "提升自身240攻击和对敌人前排12%伤害"}, {"i": 3151, "type": "item", "zh": "当魔方只剩下一种颜色时，怎么转都是正确的"}, {"i": 3152, "type": "item", "zh": "从阿修、伊丽莎白、堕珑武器中选择一个获得"}]